tfinta/__init__.py
tfinta/dart.py
tfinta/gtfs.py
tfinta/gtfs_data_model.py
tfinta/py.typed
tfinta/realtime.py
tfinta/realtime_data_model.py
tfinta/stations.py
tfinta/tfinta_base.py
tfinta/trains.py
tfinta-1.9.dist-info/licenses/LICENSE
tfinta-1.9.dist-info/METADATA
tfinta-1.9.dist-info/WHEEL
tfinta-1.9.dist-info/top_level.txt
tfinta-1.9.dist-info/RECORD
