Metadata-Version: 2.4
Name: tfinta
Version: 1.9
Summary: Python library and shell scripts for parsing and displaying Transport for Ireland (TFI/NTA) Rail and DART schedule datasets, both GTFS and realtime
Author-email: BellaKeri <BellaKeri@github.com>, Daniel Balparda <balparda@github.com>
License-Expression: Apache-2.0
Project-URL: Homepage, https://github.com/BellaKeri/TFINTA
Project-URL: PyPI, https://pypi.org/project/tfinta/
Classifier: Programming Language :: Python :: 3
Classifier: Programming Language :: Python :: 3.11
Classifier: Programming Language :: Python :: 3.12
Classifier: Programming Language :: Python :: 3.13
Classifier: Operating System :: OS Independent
Classifier: Topic :: Utilities
Requires-Python: >=3.11.13
License-File: LICENSE
Requires-Dist: prettytable<4.0,>=3.16
Requires-Dist: balparda-baselib<2.0,>=1.11
Dynamic: license-file
